{
  "compilerOptions": {
    "baseUrl": ".",
    "paths": {
      "@/*": [
        "*"
      ],
      "@src/*": [
        "src/*"
      ],
      "@pages/*": [
        "src/pages/*"
      ],
      "@components/*": [
        "src/components/*"
      ],
      "@router/*": [
        "src/router/*"
      ],
      "@assets/*": [
        "src/assets/*"
      ],
      "@store/*": [
        "src/store/*"
      ],
      "@hooks/*": [
        "src/hooks/*"
      ],
      "@contexts/*": [
        "src/contexts/*"
      ],
      "@api/*": [
        "src/api/*"
      ]
    }
  }
}
